knossos/__init__.py
knossos/__main__.py
knossos/auto_fetch.py
knossos/bool_parser.py
knossos/center.py
knossos/clibs.py
knossos/integration.py
knossos/ipc.py
knossos/launcher.py
knossos/nebula.py
knossos/parsetab.py
knossos/progress.py
knossos/py2_compat.py
knossos/qt.py
knossos/repo.py
knossos/runner.py
knossos/settings.py
knossos/tasks.py
knossos/util.py
knossos/vplib.py
knossos/web.py
knossos/windows.py
knossos/data/hlp.icns
knossos/data/hlp.ico
knossos/data/hlp.png
knossos/data/resources.qrc
knossos/data/resources.rcc
knossos/third_party/__init__.py
knossos/third_party/cpuinfo.py
knossos/ui/__init__.py
knossos/ui/edit_description.py
knossos/ui/flags.py
knossos/ui/gogextract.py
knossos/ui/hell.py
knossos/ui/install.py
knossos/ui/log_viewer.py
knossos/ui/mod_settings.py
knossos/ui/mod_versions.py
knossos/ui/select_list.py
knossos-0.7.1.dist-info/DESCRIPTION.rst
knossos-0.7.1.dist-info/METADATA
knossos-0.7.1.dist-info/RECORD
knossos-0.7.1.dist-info/WHEEL
knossos-0.7.1.dist-info/entry_points.txt
knossos-0.7.1.dist-info/metadata.json
knossos-0.7.1.dist-info/top_level.txt
